rer.bandi-4.3.0-py3.10-nspkg.pth
rer/bandi/__init__.py
rer/bandi/configure.zcml
rer/bandi/i18n.sh
rer/bandi/indexer.py
rer/bandi/query_index_modifiers.py
rer/bandi/querymodifiers.zcml
rer/bandi/setuphandlers.py
rer/bandi/testing.py
rer/bandi/upgrades.py
rer/bandi/upgrades.zcml
rer/bandi/Extensions/Install.py
rer/bandi/Extensions/__init__.py
rer/bandi/adapters/__init__.py
rer/bandi/adapters/configure.zcml
rer/bandi/adapters/custom_filters.py
rer/bandi/browser/__init__.py
rer/bandi/browser/bando-right.pt
rer/bandi/browser/bando.pt
rer/bandi/browser/bando.py
rer/bandi/browser/collection.pt
rer/bandi/browser/collection.py
rer/bandi/browser/configure.zcml
rer/bandi/browser/context.py
rer/bandi/browser/search.pt
rer/bandi/browser/search.py
rer/bandi/browser/search_form.pt
rer/bandi/browser/search_rest.pt
rer/bandi/browser/search_rest.py
rer/bandi/browser/searchbandi.js
rer/bandi/browser/css/Makefile
rer/bandi/browser/css/bandi.css
rer/bandi/browser/css/bandi.css.map
rer/bandi/browser/css/bandi.scss
rer/bandi/browser/images/bando.png
rer/bandi/browser/images/bando_closed.png
rer/bandi/browser/images/bando_icon.svg
rer/bandi/browser/images/bando_inprogress.png
rer/bandi/browser/images/bando_open.png
rer/bandi/browser/images/folder_bando_deep.gif
rer/bandi/browser/static/.gitkeep
rer/bandi/browser/static/dist/prod/main.css
rer/bandi/browser/static/dist/prod/main.css.map
rer/bandi/browser/static/dist/prod/main.js
rer/bandi/browser/static/dist/prod/main.js.map
rer/bandi/browser/static/javascripts/App.js
rer/bandi/browser/static/javascripts/App.less
rer/bandi/browser/static/javascripts/TranslationsContext.js
rer/bandi/browser/static/javascripts/index.js
rer/bandi/browser/static/javascripts/components/BandoItem/index.js
rer/bandi/browser/static/javascripts/components/BandoItem/index.less
rer/bandi/browser/static/javascripts/components/FiltersWrapper/index.js
rer/bandi/browser/static/javascripts/components/FiltersWrapper/index.less
rer.bandi-4.3.0.dist-info/METADATA
rer.bandi-4.3.0.dist-info/WHEEL
rer.bandi-4.3.0.dist-info/entry_points.txt
rer.bandi-4.3.0.dist-info/namespace_packages.txt
rer.bandi-4.3.0.dist-info/top_level.txt
rer.bandi-4.3.0.dist-info/RECORD
