Metadata-Version: 2.1
Name: rer.bandi
Version: 4.3.0
Summary: A product for announcements management
Home-page: https://github.com/PloneGov-IT/rer.bandi
Author: RedTurtle Technology
Author-email: sviluppoplone@redturtle.it
License: GPL
Project-URL: PyPI, https://pypi.python.org/pypi/rer.bandi
Project-URL: Source, https://github.com/PloneGov-IT/rer.bandi
Project-URL: Tracker, https://github.com/PloneGov-IT/rer.bandi/issues
Keywords: rer bandi announcements
Classifier: Environment :: Web Environment
Classifier: Framework :: Plone :: 5.1
Classifier: Framework :: Plone :: 5.2
Classifier: Framework :: Plone :: Addon
Classifier: Framework :: Plone
Classifier: License :: OSI Approved :: GNU General Public License v2 (GPLv2)
Classifier: Operating System :: OS Independent
Classifier: Programming Language :: Python :: 2.7
Classifier: Programming Language :: Python :: 3.6
Classifier: Programming Language :: Python :: 3.7
Classifier: Programming Language :: Python
Requires-Dist: setuptools
Requires-Dist: lxml
Requires-Dist: plone.restapi
Provides-Extra: test
Requires-Dist: plone.app.testing ; extra == 'test'
Requires-Dist: plone.testing >=5.0.0 ; extra == 'test'
Requires-Dist: plone.app.contenttypes ; extra == 'test'
Requires-Dist: plone.app.robotframework[debug] ; extra == 'test'
Requires-Dist: requests ; extra == 'test'
